devhelper/__init__.py
devhelper/cli.py
devhelper/solution_parser.py
devhelper/tasks.py
devhelper_carlosruc-0.1.2.dist-info/licenses/LICENSE
devhelper_carlosruc-0.1.2.dist-info/METADATA
devhelper_carlosruc-0.1.2.dist-info/WHEEL
devhelper_carlosruc-0.1.2.dist-info/entry_points.txt
devhelper_carlosruc-0.1.2.dist-info/top_level.txt
devhelper_carlosruc-0.1.2.dist-info/RECORD
