Metadata-Version: 2.4
Name: devhelper-carlosruc
Version: 0.1.2
Summary: CLI to automate dev tasks
Author: Carlos Escalona
License-File: LICENSE
Requires-Dist: click
Dynamic: license-file
